trevi/__init__.py
trevi/profiles/app_config.py
trevi/profiles/config_paths.py
trevi/profiles/profile_utils.py
trevi/protos/rome/configurations/backtest/clock_conf_pb2.py
trevi/protos/rome/configurations/backtest/clock_conf_pb2.pyi
trevi/protos/rome/configurations/backtest/clock_conf_pb2_grpc.py
trevi/protos/rome/configurations/backtest/source_streams/crypto/tick_pub_conf_pb2.py
trevi/protos/rome/configurations/backtest/source_streams/crypto/tick_pub_conf_pb2.pyi
trevi/protos/rome/configurations/backtest/source_streams/crypto/tick_pub_conf_pb2_grpc.py
trevi/protos/rome/events/event_pb2.py
trevi/protos/rome/events/event_pb2.pyi
trevi/protos/rome/events/event_pb2_grpc.py
trevi/protos/rome/events/order_pb2.py
trevi/protos/rome/events/order_pb2.pyi
trevi/protos/rome/events/order_pb2_grpc.py
trevi/protos/rome/events/transaction_pb2.py
trevi/protos/rome/events/transaction_pb2.pyi
trevi/protos/rome/events/transaction_pb2_grpc.py
trevi/protos/rome/ostream_conf_pb2.py
trevi/protos/rome/ostream_conf_pb2.pyi
trevi/protos/rome/ostream_conf_pb2_grpc.py
trevi/protos/rome/rome.desc
trevi/protos/rome/services/broker_gateway_pb2.py
trevi/protos/rome/services/broker_gateway_pb2.pyi
trevi/protos/rome/services/broker_gateway_pb2_grpc.py
trevi/protos/rome/services/fund_manager_pb2.py
trevi/protos/rome/services/fund_manager_pb2.pyi
trevi/protos/rome/services/fund_manager_pb2_grpc.py
trevi/protos/rome/services/portfolio_manager_pb2.py
trevi/protos/rome/services/portfolio_manager_pb2.pyi
trevi/protos/rome/services/portfolio_manager_pb2_grpc.py
trevi/protos/rome/signal_pb2.py
trevi/protos/rome/signal_pb2.pyi
trevi/protos/rome/signal_pb2_grpc.py
trevi/protos/rome/signals_conf_pb2.py
trevi/protos/rome/signals_conf_pb2.pyi
trevi/protos/rome/signals_conf_pb2_grpc.py
trevi/protos/rome/strategies/three_up_tick_conf_pb2.py
trevi/protos/rome/strategies/three_up_tick_conf_pb2.pyi
trevi/protos/rome/strategies/three_up_tick_conf_pb2_grpc.py
trevi/protos/rome/tick_pb2.py
trevi/protos/rome/tick_pb2.pyi
trevi-0.1.1.dist-info/METADATA
trevi-0.1.1.dist-info/WHEEL
trevi-0.1.1.dist-info/RECORD
