Metadata-Version: 2.1
Name: trevi
Version: 0.1.1
Summary: 
Author: Ehud Adler
Author-email: easports96@gmail.com
Requires-Python: >=3.10,<4.0
Classifier: Programming Language :: Python :: 3
Classifier: Programming Language :: Python :: 3.10
Classifier: Programming Language :: Python :: 3.11
Classifier: Programming Language :: Python :: 3.12
Provides-Extra: redis
Requires-Dist: HeapDict (>=1.0.1,<2.0.0)
Requires-Dist: Requests (>=2.31.0,<3.0.0)
Requires-Dist: XlsxWriter (>=3.1.9,<4.0.0)
Requires-Dist: alpaca-py (>=0.20.3,<0.21.0)
Requires-Dist: black (>=24.4.1,<25.0.0)
Requires-Dist: celery (>=5.4.0,<6.0.0) ; extra == "redis"
Requires-Dist: celery[redis] (>=5.4.0,<6.0.0) ; extra == "redis"
Requires-Dist: coinbase-advanced-py (>=1.2.2,<2.0.0)
Requires-Dist: dash (>=2.16.1,<3.0.0)
Requires-Dist: duckdb (>=0.10.3,<0.11.0)
Requires-Dist: flower (>=2.0.1,<3.0.0)
Requires-Dist: grpcio (>=1.63.0,<2.0.0)
Requires-Dist: grpcio-health-checking (>=1.63.0,<2.0.0)
Requires-Dist: grpcio-reflection (>=1.63.0,<2.0.0)
Requires-Dist: grpcio-tools (>=1.63.0,<2.0.0)
Requires-Dist: ipykernel (>=6.29.5,<7.0.0)
Requires-Dist: kafka-python (>=2.0.2,<3.0.0)
Requires-Dist: mockito (>=1.5.0,<2.0.0)
Requires-Dist: numpy (>=1.24.2,<2.0.0)
Requires-Dist: pandas (>=2.0.0,<3.0.0)
Requires-Dist: plotly (>=5.18.0,<6.0.0)
Requires-Dist: protobuf (>=5.26.1,<6.0.0)
Requires-Dist: psycopg2-binary (>=2.9.9,<3.0.0)
Requires-Dist: pyarrow (>=16.1.0,<17.0.0)
Requires-Dist: pyfolio-reloaded (>=0.9.7,<0.10.0)
Requires-Dist: pytest (>=8.1.1,<9.0.0)
Requires-Dist: pytz (>=2023.3,<2024.0)
Requires-Dist: pyyaml (>=6.0.1,<7.0.0)
Requires-Dist: redis (>=5.0.4,<6.0.0)
Requires-Dist: sqlalchemy (>=2.0.29,<3.0.0)
Requires-Dist: tox (>=4.14.2,<5.0.0)
Requires-Dist: tqdm (>=4.65.0,<5.0.0)
